[
    {
        "name": "Test level",
        "imageOriginal": {},
        "imageDiff": {},
        "nbDifferences": 10,
        "isEasy": "true",
        "clusters": [
            [1, 1],
            [1, 1]
        ]
    },
    {
        "id": 2,
        "name": "Test level",
        "playerSolo": ["Bot1", "Bot2", "Bot3"],
        "timeSolo": [60, 65, 70],
        "playerMulti": ["Bot1", "Bot2", "Bot3"],
        "timeMulti": [80, 83, 90],
        "isEasy": true,
        "nbDifferences": 10
    }
]
